{
  "schema_version": "1.0",
  "generated_at": "2026-05-13T04:33:21+00:00",
  "list": {
    "list_id": "2053094822601425075",
    "name": "x_list_2053094822601425075",
    "category": "uncategorized",
    "tags": [],
    "description": "",
    "source_url": "https://x.com/i/lists/2053094822601425075",
    "github_dir": "x_list_members/data/exports/lists/x_list_2053094822601425075"
  },
  "outputs": {
    "recommended_members": "data/exports/lists/x_list_2053094822601425075/recommended_members.json",
    "members_full": "data/exports/lists/x_list_2053094822601425075/members_full.json",
    "members_handles": "data/exports/lists/x_list_2053094822601425075/members_handles.json"
  },
  "member_count": 15,
  "handles": [
    "@juesaiquan",
    "@zzc_ae",
    "@Mojito_cx",
    "@Feng_btc",
    "@2568hgg",
    "@YL20020628",
    "@frankyleon725",
    "@Rocky_Eths",
    "@qntnghn1",
    "@Reboottttttt",
    "@LawrenceEros",
    "@u9_BlockChain",
    "@ChinaWeb3",
    "@798_eth",
    "@aiqiang888"
  ],
  "members": [
    {
      "id": "1895005913964257280",
      "name": "梦想进入决赛圈",
      "screen_name": "juesaiquan",
      "url": "https://x.com/juesaiquan",
      "description": "就爱打新，好的会发，注意风险，盈亏自负。",
      "followers_count": 4157,
      "friends_count": 985,
      "statuses_count": 2186,
      "listed_count": 75,
      "created_at": "Thu Feb 27 07:00:05 +0000 2025",
      "verified": false,
      "blue_verified": true,
      "protected": false,
      "profile_image_url": "https://pbs.twimg.com/profile_images/2039546392591699968/CiG0xTz9_normal.jpg"
    },
    {
      "id": "1870802821244739585",
      "name": "zzc",
      "screen_name": "zzc_ae",
      "url": "https://x.com/zzc_ae",
      "description": "Alpha 投研 |  坚定持有 BNB | 币安人生\n\n币安钱包交易：https://t.co/5A4skboy2o\ngmgn交易：https://t.co/0GIfytQGfc\n进入频道获取信息⬇️",
      "followers_count": 5185,
      "friends_count": 682,
      "statuses_count": 2582,
      "listed_count": 106,
      "created_at": "Sun Dec 22 12:05:42 +0000 2024",
      "verified": false,
      "blue_verified": true,
      "protected": false,
      "profile_image_url": "https://pbs.twimg.com/profile_images/2030466059850153984/7vQGiZnp_normal.jpg"
    },
    {
      "id": "1869344314314436608",
      "name": "Mojito",
      "screen_name": "Mojito_cx",
      "url": "https://x.com/Mojito_cx",
      "description": "07年｜链上交易员｜数据分析｜alpha机会｜  Ru7老师小助理 仅供参考，不构成任何投资建议 DYOR tg：@mojito_cx",
      "followers_count": 3409,
      "friends_count": 1307,
      "statuses_count": 2119,
      "listed_count": 56,
      "created_at": "Wed Dec 18 11:30:05 +0000 2024",
      "verified": false,
      "blue_verified": true,
      "protected": false,
      "profile_image_url": "https://pbs.twimg.com/profile_images/2025584687834595328/Y4Jc1NgG_normal.jpg"
    },
    {
      "id": "1858198810226499584",
      "name": "币胜客",
      "screen_name": "Feng_btc",
      "url": "https://x.com/Feng_btc",
      "description": "专注加密 🎁 日更的撸毛博主｜只发自己在跟项目 ｜热点项目投研｜meme冲狗选手｜ 主打保姆式教程｜打新/打狗/铭文/NFT 样样沾边\n💌欢迎宣发合作：X私信或 TG：Bishengk \n\n⭐ 肉体在Web2，灵魂已上链｜赚钱养梦\n撸毛交流群：https://t.co/CuQANtZ3rN",
      "followers_count": 13190,
      "friends_count": 3248,
      "statuses_count": 13490,
      "listed_count": 119,
      "created_at": "Sun Nov 17 17:21:43 +0000 2024",
      "verified": false,
      "blue_verified": true,
      "protected": false,
      "profile_image_url": "https://pbs.twimg.com/profile_images/1858198945857732608/fdoSsUUq_normal.jpg"
    },
    {
      "id": "1781365222193655808",
      "name": "梦想做掏钱大手子",
      "screen_name": "2568hgg",
      "url": "https://x.com/2568hgg",
      "description": "努力成为链上掏钱选手，不断学习中  技术小白  钻石手",
      "followers_count": 166,
      "friends_count": 221,
      "statuses_count": 940,
      "listed_count": 2,
      "created_at": "Fri Apr 19 16:52:40 +0000 2024",
      "verified": false,
      "blue_verified": false,
      "protected": false,
      "profile_image_url": "https://pbs.twimg.com/profile_images/2034603331285553152/KWwv5gbc_normal.jpg"
    },
    {
      "id": "1774099089636167680",
      "name": "链上猎手 PI BUILDER",
      "screen_name": "YL20020628",
      "url": "https://x.com/YL20020628",
      "description": "bybit:\nhttps://t.co/yT8BwfHhP2\n手动返佣20%\nodin小猎手，盈亏自负，买卖自由\n铭文|符文|alkanes 生态参与者",
      "followers_count": 1257,
      "friends_count": 1619,
      "statuses_count": 1837,
      "listed_count": 29,
      "created_at": "Sat Mar 30 15:39:30 +0000 2024",
      "verified": false,
      "blue_verified": true,
      "protected": false,
      "profile_image_url": "https://pbs.twimg.com/profile_images/2038625665428398080/yTABR-AO_normal.jpg"
    },
    {
      "id": "1761401795916767232",
      "name": "Franky",
      "screen_name": "frankyleon725",
      "url": "https://x.com/frankyleon725",
      "description": "Create | Gambler & Ponzi | Bullish | Roving Critic | Fitness\n\nI trade and sell volatility",
      "followers_count": 1333,
      "friends_count": 483,
      "statuses_count": 2256,
      "listed_count": 9,
      "created_at": "Sat Feb 24 14:45:03 +0000 2024",
      "verified": false,
      "blue_verified": true,
      "protected": false,
      "profile_image_url": "https://pbs.twimg.com/profile_images/1976489809268097024/SqJX9xUy_normal.jpg"
    },
    {
      "id": "1687286859876237312",
      "name": "Rocky",
      "screen_name": "Rocky_Eths",
      "url": "https://x.com/Rocky_Eths",
      "description": "📄个人操作记录，不做投资建议！ \n💌项目合作：https://t.co/1zKsMfmzAX \nOKX Web3钱包现已支持130+公链\n#OKX DEX 最高返佣 邀请码：ROCKY2\n注册链接：https://t.co/h9CglihLkA",
      "followers_count": 25789,
      "friends_count": 2020,
      "statuses_count": 17252,
      "listed_count": 409,
      "created_at": "Fri Aug 04 02:18:42 +0000 2023",
      "verified": false,
      "blue_verified": true,
      "protected": false,
      "profile_image_url": "https://pbs.twimg.com/profile_images/2005202248784384000/zu8M0zmx_normal.jpg"
    },
    {
      "id": "1565289526729252875",
      "name": "Crypto 黑",
      "screen_name": "qntnghn1",
      "url": "https://x.com/qntnghn1",
      "description": "恭喜你被我恭喜到了\n打新、撸毛、合约、二级选手\n主打技多不压身。\n哪个赚钱就整哪个。\n\n下面是TG的撸毛交流群~~",
      "followers_count": 5084,
      "friends_count": 1070,
      "statuses_count": 2801,
      "listed_count": 93,
      "created_at": "Thu Sep 01 10:45:00 +0000 2022",
      "verified": false,
      "blue_verified": true,
      "protected": false,
      "profile_image_url": "https://pbs.twimg.com/profile_images/1822352276159340544/kah2LsDR_normal.jpg"
    },
    {
      "id": "1461650068075806722",
      "name": "Reboot.Btc",
      "screen_name": "Reboottttttt",
      "url": "https://x.com/Reboottttttt",
      "description": "Co-Founder @ArcadyWeb3 Ambassador  @arbitrum \n今年专注Ai 港股 打新 定投BTC \n商务联系:dc:reboot7454 TG:@Reboot7454\n推特当朋友圈发的 别乱买 盈亏自负 爹妈们",
      "followers_count": 19406,
      "friends_count": 10926,
      "statuses_count": 113075,
      "listed_count": 231,
      "created_at": "Fri Nov 19 10:58:33 +0000 2021",
      "verified": false,
      "blue_verified": true,
      "protected": false,
      "profile_image_url": "https://pbs.twimg.com/profile_images/2045007928537817088/jJOzirj9_normal.jpg"
    },
    {
      "id": "1441398385022361600",
      "name": "Erock | 老衲 🙏",
      "screen_name": "LawrenceEros",
      "url": "https://x.com/LawrenceEros",
      "description": "Hi I’m Erock a.k.a 老衲.\n\nNFT player since 10-2021...\n\nP.S: NFT 赚不赚钱不重要🤣 主要是刺激～~\n\nNow i'm just a Digital Slop..",
      "followers_count": 5135,
      "friends_count": 7310,
      "statuses_count": 30179,
      "listed_count": 46,
      "created_at": "Fri Sep 24 13:45:40 +0000 2021",
      "verified": false,
      "blue_verified": true,
      "protected": false,
      "profile_image_url": "https://pbs.twimg.com/profile_images/2053132553742336000/h3DCKtD4_normal.jpg"
    },
    {
      "id": "1420805364279218177",
      "name": "U9Labs",
      "screen_name": "u9_BlockChain",
      "url": "https://x.com/u9_BlockChain",
      "description": "专注市场资讯、撸毛、一级二级投研 合作请DM丨转载请注明出处 公众号：U9BlockChain\n项目合作：https://t.co/wsZqw5BaoB\n#OKX 最高返 邀请码：U9LABS\n注册链接：https://t.co/RXTdbNws2q",
      "followers_count": 36199,
      "friends_count": 1783,
      "statuses_count": 5652,
      "listed_count": 103,
      "created_at": "Thu Jul 29 17:56:12 +0000 2021",
      "verified": false,
      "blue_verified": true,
      "protected": false,
      "profile_image_url": "https://pbs.twimg.com/profile_images/1482235352035500034/wSb0XMmx_normal.jpg"
    },
    {
      "id": "1398626069817618434",
      "name": "luckytime.eth",
      "screen_name": "ChinaWeb3",
      "url": "https://x.com/ChinaWeb3",
      "description": "NFT深度套牢，meme币专业接盘侠，撸毛界官方认证电子乞丐",
      "followers_count": 2602,
      "friends_count": 2663,
      "statuses_count": 2318,
      "listed_count": 27,
      "created_at": "Sat May 29 13:03:48 +0000 2021",
      "verified": false,
      "blue_verified": true,
      "protected": false,
      "profile_image_url": "https://pbs.twimg.com/profile_images/1902597655672614912/BGIWhKdH_normal.jpg"
    },
    {
      "id": "1080717364151402502",
      "name": "798.eth 🍌🌍☮️🗡️👁️",
      "screen_name": "798_eth",
      "url": "https://x.com/798_eth",
      "description": "Less #trust more #truth · | Meta Foxes #192 · | meebits 中文社区创建者 · | @PANews 入驻专栏作者\nContact：https://t.co/FtYywI1QtP\nhttps://t.co/OQ81ynt2Qy",
      "followers_count": 9766,
      "friends_count": 6289,
      "statuses_count": 3502,
      "listed_count": 193,
      "created_at": "Thu Jan 03 06:47:53 +0000 2019",
      "verified": false,
      "blue_verified": true,
      "protected": false,
      "profile_image_url": "https://pbs.twimg.com/profile_images/1798375395659800576/NM3cBcCZ_normal.jpg"
    },
    {
      "id": "786662054",
      "name": "记得爱强",
      "screen_name": "aiqiang888",
      "url": "https://x.com/aiqiang888",
      "description": "我是撸毛小白，我有两只小狗，一只叫多多，一只叫元宝。 \n商务合作       TG: kas_silver      #蓝鸟会 #灯塔",
      "followers_count": 12625,
      "friends_count": 3614,
      "statuses_count": 23145,
      "listed_count": 89,
      "created_at": "Tue Aug 28 09:58:29 +0000 2012",
      "verified": false,
      "blue_verified": true,
      "protected": false,
      "profile_image_url": "https://pbs.twimg.com/profile_images/1973882737632391168/37cVOJSJ_normal.jpg"
    }
  ]
}
